ml_python_lib/__init__.py
ml_python_lib/import_data/__init__.py
ml_python_lib/import_data/import_data.py
ml_python_lib/import_data/prepare_gscv2.py
ml_python_lib/preprocess/__init__.py
ml_python_lib/preprocess/preprocessor.py
ml_python_lib-0.2.0.dist-info/WHEEL
ml_python_lib-0.2.0.dist-info/METADATA
ml_python_lib-0.2.0.dist-info/RECORD
