Metadata-Version: 2.1
Name: ml-python-lib
Version: 0.2.0
Summary: Machine Learning Library for tensorflow training algorithms
Author: Tanguy Coatalem
Author-email: tanguy.coatalem@cogneed.ai
Requires-Python: >=3.6,<4.0
Classifier: Programming Language :: Python :: 3
Classifier: Programming Language :: Python :: 3.6
Classifier: Programming Language :: Python :: 3.7
Classifier: Programming Language :: Python :: 3.8
Classifier: Programming Language :: Python :: 3.9
Requires-Dist: dynaconf (>=3.1.2,<4.0.0)
Requires-Dist: keyring (>=21.5.0,<22.0.0)
Requires-Dist: pydub (>=0.24.1,<0.25.0)
Requires-Dist: tensorflow (>=2.3.1,<3.0.0)
